diaosigui/__init__.py
diaosigui-1.0.3.dist-info/METADATA
diaosigui-1.0.3.dist-info/WHEEL
diaosigui-1.0.3.dist-info/top_level.txt
diaosigui-1.0.3.dist-info/RECORD
