Metadata-Version: 2.1
Name: diaosigui
Version: 1.0.3
Summary: A small example package
Author: CJkim
Author-email: kim20081123@dingtalk.com
License: BSD License
Platform: all
Classifier: Intended Audience :: Developers
Classifier: Natural Language :: Chinese (Simplified)
Classifier: Programming Language :: Python
Classifier: Programming Language :: Python :: 3
Classifier: Programming Language :: Python :: 3.5
Classifier: Programming Language :: Python :: 3.6
Classifier: Programming Language :: Python :: 3.7
Classifier: Programming Language :: Python :: 3.8
